fragmenstein/__init__.py
fragmenstein/branding.py
fragmenstein/display.py
fragmenstein/divergent_colors.json
fragmenstein/legacy.py
fragmenstein/m_rmsd.py
fragmenstein/cli/__init__.py
fragmenstein/demo/__init__.py
fragmenstein/demo/_base_dataset_holder.py
fragmenstein/demo/mac1_mols/__init__.py
fragmenstein/demo/mac1_mols/diamond-x0091_B.mol
fragmenstein/demo/mac1_mols/diamond-x0104_A.mol
fragmenstein/demo/mac1_mols/diamond-x0128_A.mol
fragmenstein/demo/mac1_mols/diamond-x0142_A.mol
fragmenstein/demo/mac1_mols/diamond-x0158_B.mol
fragmenstein/demo/mac1_mols/diamond-x0159_B.mol
fragmenstein/demo/mac1_mols/diamond-x0173_B.mol
fragmenstein/demo/mac1_mols/diamond-x0216_A.mol
fragmenstein/demo/mac1_mols/diamond-x0228_B.mol
fragmenstein/demo/mac1_mols/diamond-x0253_A.mol
fragmenstein/demo/mac1_mols/diamond-x0259_A.mol
fragmenstein/demo/mac1_mols/diamond-x0282_A.mol
fragmenstein/demo/mac1_mols/diamond-x0290_A.mol
fragmenstein/demo/mac1_mols/diamond-x0299_A.mol
fragmenstein/demo/mac1_mols/diamond-x0301_B.mol
fragmenstein/demo/mac1_mols/diamond-x0334_A.mol
fragmenstein/demo/mac1_mols/diamond-x0371_A.mol
fragmenstein/demo/mac1_mols/diamond-x0380_B.mol
fragmenstein/demo/mac1_mols/diamond-x0417_B.mol
fragmenstein/demo/mac1_mols/diamond-x0421_A.mol
fragmenstein/demo/mac1_mols/diamond-x0423_B.mol
fragmenstein/demo/mac1_mols/diamond-x0436_B.mol
fragmenstein/demo/mac1_mols/diamond-x0438_A.mol
fragmenstein/demo/mac1_mols/diamond-x0465_A.mol
fragmenstein/demo/mac1_mols/diamond-x0469_B.mol
fragmenstein/demo/mac1_mols/diamond-x0471_A.mol
fragmenstein/demo/mac1_mols/diamond-x0496_A.mol
fragmenstein/demo/mac1_mols/diamond-x0516_A.mol
fragmenstein/demo/mac1_mols/diamond-x0524_A.mol
fragmenstein/demo/mac1_mols/diamond-x0548_A.mol
fragmenstein/demo/mac1_mols/diamond-x0548_B.mol
fragmenstein/demo/mac1_mols/diamond-x0574_A.mol
fragmenstein/demo/mac1_mols/diamond-x0587_A.mol
fragmenstein/demo/mac1_mols/diamond-x0591_A.mol
fragmenstein/demo/mac1_mols/diamond-x0592_A.mol
Fragmenstein-0.9.3.dist-info/LICENSE
Fragmenstein-0.9.3.dist-info/METADATA
Fragmenstein-0.9.3.dist-info/WHEEL
Fragmenstein-0.9.3.dist-info/entry_points.txt
Fragmenstein-0.9.3.dist-info/top_level.txt
Fragmenstein-0.9.3.dist-info/RECORD
