Metadata-Version: 2.1
Name: Fragmenstein
Version: 0.9.3
Summary: Scaffold hopping between bound compounds by stitching them together like a reanimated corpse
Home-page: https://github.com/matteoferla/Fragmenstein
Author: Matteo Ferla
Author-email: matteo.ferla@gmail.com
License: MIT
Classifier: Development Status :: 4 - Beta
Classifier: Intended Audience :: Science/Research
Classifier: Topic :: Scientific/Engineering :: Bio-Informatics
Classifier: Topic :: Scientific/Engineering :: Chemistry
Classifier: License :: OSI Approved :: MIT License
Classifier: Programming Language :: Python :: 3.7
Classifier: Programming Language :: Python :: 3.8
Classifier: Programming Language :: Python :: 3.9
Requires-Python: >=3.7
License-File: LICENSE
Requires-Dist: requests (>=2.27.1)
Requires-Dist: ipython (>=8.3.0)
Requires-Dist: numpy (>=1.22.4)
Requires-Dist: scipy (>=1.8.1)
Requires-Dist: pandas (>=1.4.2)
Requires-Dist: pebble (>=4.6.3)
Requires-Dist: nglview (>=3.0.3)
Requires-Dist: rdkit-pypi (>=2022.3.2.1)
Requires-Dist: rdkit-to-params (>=1.2.1)
Requires-Dist: molecular-rectifier (>=0.1.6)
Requires-Dist: singledispatchmethod (>=1.0)
Requires-Dist: typing-extensions (>=4.2.0)
Requires-Dist: matplotlib (>=3.5.2)
Requires-Dist: smallworld-api (>=1.1)
Requires-Dist: sqlitedict (>=2.0.0)
Provides-Extra: jupyter
Requires-Dist: jupyter ; extra == 'jupyter'
